Metadata-Version: 1.1
Name: deepinsight
Version: 0.0.0
Summary: 
